[
  {
    "posicao": 1,
    "placa": "QBK9J16",
    "produto": "Cimento ensacado",
    "tipo": "TRANSFEFÊNCIA"
  },
  {
    "posicao": 2,
    "placa": "RTI4E59",
    "produto": "Cimento ensacado",
    "tipo": "TRANSFEFÊNCIA"
  },
  {
    "posicao": 3,
    "placa": "NVP6G66",
    "produto": "Cimento ensacado",
    "tipo": "TRANSFEFÊNCIA"
  },
  {
    "posicao": 4,
    "placa": "CPG8B90",
    "produto": "Cimento ensacado",
    "tipo": "TRANSFEFÊNCIA"
  },
  {
    "posicao": 5,
    "placa": "KXI9B07",
    "produto": "Cimento ensacado",
    "tipo": "TRANSFEFÊNCIA"
  },
  {
    "posicao": 6,
    "placa": "OAX0A08",
    "produto": "Cimento ensacado",
    "tipo": "TRANSFEFÊNCIA"
  },
  {
    "posicao": 7,
    "placa": "QAH1G95",
    "produto": "Cimento ensacado",
    "tipo": "TRANSFEFÊNCIA"
  },
  {
    "posicao": 8,
    "placa": "HNM3C88",
    "produto": "Cimento ensacado",
    "tipo": "FOB"
  },
  {
    "posicao": 9,
    "placa": "HBN5J98",
    "produto": "Cimento ensacado",
    "tipo": "FOB"
  },
  {
    "posicao": 10,
    "placa": "TDN5E72",
    "produto": "Cimento ensacado",
    "tipo": "FOB"
  },
  {
    "posicao": 11,
    "placa": "GVK0164",
    "produto": "Cimento ensacado",
    "tipo": "FOB"
  },
  {
    "posicao": 12,
    "placa": "HNX2F44",
    "produto": "Cimento ensacado",
    "tipo": "FOB"
  }
]
