[
  {
    "posicao": 1,
    "placa": "RXO5C43",
    "produto": "Cimento ensacado",
    "tipo": "FOB"
  },
  {
    "posicao": 2,
    "placa": "BAG2A22",
    "produto": "Cimento ensacado",
    "tipo": "FOB"
  },
  {
    "posicao": 3,
    "placa": "BZL6C00",
    "produto": "Cimento ensacado",
    "tipo": "FOB"
  },
  {
    "posicao": 4,
    "placa": "EJW9D94",
    "produto": "Cimento ensacado",
    "tipo": "FOB"
  },
  {
    "posicao": 5,
    "placa": "QXY9E78",
    "produto": "Cimento ensacado",
    "tipo": "FOB"
  },
  {
    "posicao": 6,
    "placa": "MIT7D84",
    "produto": "Cimento ensacado",
    "tipo": "FOB"
  },
  {
    "posicao": 7,
    "placa": "FEJ6436",
    "produto": "Cimento ensacado",
    "tipo": "FOB"
  },
  {
    "posicao": 8,
    "placa": "HNM3558",
    "produto": "Cimento ensacado",
    "tipo": "FOB"
  },
  {
    "posicao": 9,
    "placa": "SEW2B24",
    "produto": "Cimento ensacado",
    "tipo": "FOB"
  },
  {
    "posicao": 10,
    "placa": "SSR6D15",
    "produto": "Cimento ensacado",
    "tipo": "FOB"
  },
  {
    "posicao": 11,
    "placa": "QOQ6B06",
    "produto": "Cimento ensacado",
    "tipo": "FOB"
  },
  {
    "posicao": 12,
    "placa": "OOW0044",
    "produto": "Cimento ensacado",
    "tipo": "FOB"
  },
  {
    "posicao": 13,
    "placa": "RTH9G81",
    "produto": "Cimento ensacado",
    "tipo": "FOB"
  },
  {
    "posicao": 14,
    "placa": "QUO1A91",
    "produto": "Cimento ensacado",
    "tipo": "FOB"
  },
  {
    "posicao": 15,
    "placa": "QOZ4B94",
    "produto": "Cimento ensacado",
    "tipo": "FOB"
  },
  {
    "posicao": 16,
    "placa": "QAJ0E20",
    "produto": "Cimento ensacado",
    "tipo": "FOB"
  },
  {
    "posicao": 17,
    "placa": "OAS2H79",
    "produto": "Cimento ensacado",
    "tipo": "FOB"
  },
  {
    "posicao": 18,
    "placa": "DPF9D23",
    "produto": "Cimento ensacado",
    "tipo": "FOB"
  },
  {
    "posicao": 19,
    "placa": "RUT3C32",
    "produto": "Cimento ensacado",
    "tipo": "FOB"
  },
  {
    "posicao": 20,
    "placa": "OLC2E12",
    "produto": "Cimento ensacado",
    "tipo": "FOB"
  }
]