[
  {
    "posicao": 1,
    "placa": "SSB8G15",
    "produto": "Cimento ensacado",
    "tipo": "FCA"
  },
  {
    "posicao": 1,
    "placa": "RXO5C43",
    "produto": "Cimento ensacado",
    "tipo": "FOB"
  },
  {
    "posicao": 2,
    "placa": "QPA4A08",
    "produto": "Cimento ensacado",
    "tipo": "FOB"
  },
  {
    "posicao": 3,
    "placa": "GBW1H23",
    "produto": "Cimento ensacado",
    "tipo": "FOB"
  },
  {
    "posicao": 4,
    "placa": "CUC7E90",
    "produto": "Cimento ensacado",
    "tipo": "FOB"
  },
  {
    "posicao": 5,
    "placa": "TEG5C77",
    "produto": "Cimento ensacado",
    "tipo": "FOB"
  },
  {
    "posicao": 6,
    "placa": "MTZ5F80",
    "produto": "Cimento ensacado",
    "tipo": "FOB"
  },
  {
    "posicao": 7,
    "placa": "AWH6I08",
    "produto": "Cimento ensacado",
    "tipo": "FOB"
  },
  {
    "posicao": 8,
    "placa": "BTR3C88",
    "produto": "Cimento ensacado",
    "tipo": "FOB"
  },
  {
    "posicao": 9,
    "placa": "GSH7A30",
    "produto": "Cimento ensacado",
    "tipo": "FOB"
  },
  {
    "posicao": 10,
    "placa": "QUG8528",
    "produto": "Cimento ensacado",
    "tipo": "FOB"
  },
  {
    "posicao": 11,
    "placa": "NKB7A40",
    "produto": "Cimento ensacado",
    "tipo": "FOB"
  },
  {
    "posicao": 12,
    "placa": "ATP2E33",
    "produto": "Cimento ensacado",
    "tipo": "FOB"
  },
  {
    "posicao": 13,
    "placa": "DOG2J31",
    "produto": "Cimento ensacado",
    "tipo": "FOB"
  },
  {
    "posicao": 14,
    "placa": "AER1I10",
    "produto": "Cimento ensacado",
    "tipo": "FOB"
  },
  {
    "posicao": 15,
    "placa": "BED3D58",
    "produto": "Cimento ensacado",
    "tipo": "FOB"
  },
  {
    "posicao": 16,
    "placa": "RMZ9D44",
    "produto": "Cimento ensacado",
    "tipo": "FOB"
  },
  {
    "posicao": 17,
    "placa": "AUC0E89",
    "produto": "Cimento ensacado",
    "tipo": "FOB"
  },
  {
    "posicao": 18,
    "placa": "EJY9I85",
    "produto": "Cimento ensacado",
    "tipo": "FOB"
  },
  {
    "posicao": 19,
    "placa": "BAG2A22",
    "produto": "Cimento ensacado",
    "tipo": "FOB"
  },
  {
    "posicao": 20,
    "placa": "RVH4C08",
    "produto": "Cimento ensacado",
    "tipo": "FOB"
  },
  {
    "posicao": 21,
    "placa": "BTB8G77",
    "produto": "Cimento ensacado",
    "tipo": "FOB"
  },
  {
    "posicao": 22,
    "placa": "GEY8C75",
    "produto": "Cimento ensacado",
    "tipo": "FOB"
  },
  {
    "posicao": 23,
    "placa": "BZL6C00",
    "produto": "Cimento ensacado",
    "tipo": "FOB"
  },
  {
    "posicao": 24,
    "placa": "EJW9D94",
    "produto": "Cimento ensacado",
    "tipo": "FOB"
  },
  {
    "posicao": 25,
    "placa": "QXY9E78",
    "produto": "Cimento ensacado",
    "tipo": "FOB"
  },
  {
    "posicao": 26,
    "placa": "MIT7D84",
    "produto": "Cimento ensacado",
    "tipo": "FOB"
  },
  {
    "posicao": 27,
    "placa": "FEJ6436",
    "produto": "Cimento ensacado",
    "tipo": "FOB"
  },
  {
    "posicao": 28,
    "placa": "HNM3558",
    "produto": "Cimento ensacado",
    "tipo": "FOB"
  },
  {
    "posicao": 29,
    "placa": "CUA7E79",
    "produto": "Cimento ensacado",
    "tipo": "FOB"
  },
  {
    "posicao": 30,
    "placa": "SEW2B24",
    "produto": "Cimento ensacado",
    "tipo": "FOB"
  },
  {
    "posicao": 31,
    "placa": "SSR6D15",
    "produto": "Cimento ensacado",
    "tipo": "FOB"
  },
  {
    "posicao": 32,
    "placa": "QOQ6B06",
    "produto": "Cimento ensacado",
    "tipo": "FOB"
  },
  {
    "posicao": 33,
    "placa": "OOW0044",
    "produto": "Cimento ensacado",
    "tipo": "FOB"
  },
  {
    "posicao": 34,
    "placa": "RTH9G81",
    "produto": "Cimento ensacado",
    "tipo": "FOB"
  },
  {
    "posicao": 35,
    "placa": "QUO1A91",
    "produto": "Cimento ensacado",
    "tipo": "FOB"
  },
  {
    "posicao": 36,
    "placa": "QOZ4B94",
    "produto": "Cimento ensacado",
    "tipo": "FOB"
  },
  {
    "posicao": 37,
    "placa": "QAJ0E20",
    "produto": "Cimento ensacado",
    "tipo": "FOB"
  }
]