[
  {
    "posicao": 1,
    "placa": "RNA6C71",
    "produto": "Cimento granel",
    "tipo": "FOB"
  },
  {
    "posicao": 2,
    "placa": "FXD9435",
    "produto": "Cimento granel",
    "tipo": "FOB"
  },
  {
    "posicao": 3,
    "placa": "FNM3C65",
    "produto": "Cimento granel",
    "tipo": "FOB"
  },
  {
    "posicao": 1,
    "placa": "GFR9H66",
    "produto": "Cimento ensacado",
    "tipo": "FOB"
  },
  {
    "posicao": 2,
    "placa": "MEC0J97",
    "produto": "Cimento ensacado",
    "tipo": "FOB"
  },
  {
    "posicao": 3,
    "placa": "SEC9F81",
    "produto": "Cimento ensacado",
    "tipo": "FOB"
  },
  {
    "posicao": 4,
    "placa": "AUT4J20",
    "produto": "Cimento ensacado",
    "tipo": "FOB"
  },
  {
    "posicao": 5,
    "placa": "RYJ4E40",
    "produto": "Cimento ensacado",
    "tipo": "FOB"
  },
  {
    "posicao": 6,
    "placa": "HMV3815",
    "produto": "Cimento ensacado",
    "tipo": "FOB"
  },
  {
    "posicao": 7,
    "placa": "RXP8I59",
    "produto": "Cimento ensacado",
    "tipo": "FOB"
  },
  {
    "posicao": 8,
    "placa": "RQR7G18",
    "produto": "Cimento ensacado",
    "tipo": "FOB"
  },
  {
    "posicao": 9,
    "placa": "BCF3H63",
    "produto": "Cimento ensacado",
    "tipo": "FOB"
  },
  {
    "posicao": 10,
    "placa": "BAP2G83",
    "produto": "Cimento ensacado",
    "tipo": "FOB"
  },
  {
    "posicao": 11,
    "placa": "QVB4233",
    "produto": "Cimento ensacado",
    "tipo": "FOB"
  },
  {
    "posicao": 12,
    "placa": "AWC0D64",
    "produto": "Cimento ensacado",
    "tipo": "FOB"
  },
  {
    "posicao": 13,
    "placa": "HBG6C31",
    "produto": "Cimento ensacado",
    "tipo": "FOB"
  },
  {
    "posicao": 14,
    "placa": "FQM4F41",
    "produto": "Cimento ensacado",
    "tipo": "FOB"
  },
  {
    "posicao": 15,
    "placa": "SDQ1B73",
    "produto": "Cimento ensacado",
    "tipo": "FOB"
  },
  {
    "posicao": 16,
    "placa": "NGF0241",
    "produto": "Cimento ensacado",
    "tipo": "FOB"
  },
  {
    "posicao": 17,
    "placa": "IIV5A08",
    "produto": "Cimento ensacado",
    "tipo": "FOB"
  },
  {
    "posicao": 18,
    "placa": "RNU2I46",
    "produto": "Cimento ensacado",
    "tipo": "FOB"
  },
  {
    "posicao": 19,
    "placa": "CTP4E11",
    "produto": "Cimento ensacado",
    "tipo": "FOB"
  },
  {
    "posicao": 20,
    "placa": "SYI7I16",
    "produto": "Cimento ensacado",
    "tipo": "FOB"
  },
  {
    "posicao": 21,
    "placa": "ASX0C63",
    "produto": "Cimento ensacado",
    "tipo": "FOB"
  },
  {
    "posicao": 22,
    "placa": "AWM5H65",
    "produto": "Cimento ensacado",
    "tipo": "FOB"
  },
  {
    "posicao": 23,
    "placa": "SFT0B40",
    "produto": "Cimento ensacado",
    "tipo": "FOB"
  },
  {
    "posicao": 24,
    "placa": "RVQ9A97",
    "produto": "Cimento ensacado",
    "tipo": "FOB"
  },
  {
    "posicao": 25,
    "placa": "QMS1A82",
    "produto": "Cimento ensacado",
    "tipo": "FOB"
  }
]