[
  {
    "posicao": 1,
    "placa": "JQI1C91",
    "produto": "Cimento granel",
    "tipo": "FOB"
  },
  {
    "posicao": 1,
    "placa": "QQH2D78",
    "produto": "Cimento ensacado",
    "tipo": "Transferencia (FCA)"
  },
  {
    "posicao": 1,
    "placa": "FTU8J47",
    "produto": "Cimento ensacado",
    "tipo": "FOB"
  },
  {
    "posicao": 2,
    "placa": "ATS3388",
    "produto": "Cimento ensacado",
    "tipo": "FOB"
  },
  {
    "posicao": 3,
    "placa": "GHH9G64",
    "produto": "Cimento ensacado",
    "tipo": "FOB"
  },
  {
    "posicao": 4,
    "placa": "AML8994",
    "produto": "Cimento ensacado",
    "tipo": "FOB"
  }
]