[
  {
    "posicao": 1,
    "placa": "OUH3A51",
    "produto": "Cimento granel",
    "tipo": "FOB"
  },
  {
    "posicao": 1,
    "placa": "SWO9H47",
    "produto": "Cimento ensacado",
    "tipo": "FOB"
  },
  {
    "posicao": 2,
    "placa": "QJN2J75",
    "produto": "Cimento ensacado",
    "tipo": "FOB"
  },
  {
    "posicao": 3,
    "placa": "OXJ2E26",
    "produto": "Cimento ensacado",
    "tipo": "FOB"
  },
  {
    "posicao": 4,
    "placa": "RNT3D59",
    "produto": "Cimento ensacado",
    "tipo": "FOB"
  },
  {
    "posicao": 5,
    "placa": "QHF6J41",
    "produto": "Cimento ensacado",
    "tipo": "FOB"
  },
  {
    "posicao": 6,
    "placa": "ATS0E58",
    "produto": "Cimento ensacado",
    "tipo": "FOB"
  },
  {
    "posicao": 7,
    "placa": "NZB4893",
    "produto": "Cimento ensacado",
    "tipo": "FOB"
  },
  {
    "posicao": 8,
    "placa": "GZV1I42",
    "produto": "Cimento ensacado",
    "tipo": "FOB"
  },
  {
    "posicao": 9,
    "placa": "BDD9A11",
    "produto": "Cimento ensacado",
    "tipo": "FOB"
  },
  {
    "posicao": 10,
    "placa": "OLL6I93",
    "produto": "Cimento ensacado",
    "tipo": "FOB"
  },
  {
    "posicao": 11,
    "placa": "BTB8G77",
    "produto": "Cimento ensacado",
    "tipo": "FOB"
  },
  {
    "posicao": 12,
    "placa": "EQC2G89",
    "produto": "Cimento ensacado",
    "tipo": "FOB"
  },
  {
    "posicao": 13,
    "placa": "QMQ4281",
    "produto": "Cimento ensacado",
    "tipo": "FOB"
  },
  {
    "posicao": 14,
    "placa": "RNQ7G36",
    "produto": "Cimento ensacado",
    "tipo": "FOB"
  },
  {
    "posicao": 15,
    "placa": "ILN3I38",
    "produto": "Cimento ensacado",
    "tipo": "FOB"
  },
  {
    "posicao": 16,
    "placa": "RTQ7C21",
    "produto": "Cimento ensacado",
    "tipo": "FOB"
  },
  {
    "posicao": 17,
    "placa": "EDQ0A41",
    "produto": "Cimento ensacado",
    "tipo": "FOB"
  },
  {
    "posicao": 18,
    "placa": "HLA4F87",
    "produto": "Cimento ensacado",
    "tipo": "FOB"
  },
  {
    "posicao": 19,
    "placa": "OPH6J71",
    "produto": "Cimento ensacado",
    "tipo": "FOB"
  },
  {
    "posicao": 20,
    "placa": "MVI7J61",
    "produto": "Cimento ensacado",
    "tipo": "FOB"
  },
  {
    "posicao": 21,
    "placa": "QXM7794",
    "produto": "Cimento ensacado",
    "tipo": "FOB"
  },
  {
    "posicao": 22,
    "placa": "RMP2D26",
    "produto": "Cimento ensacado",
    "tipo": "FOB"
  },
  {
    "posicao": 23,
    "placa": "FTU8J47",
    "produto": "Cimento ensacado",
    "tipo": "FOB"
  },
  {
    "posicao": 24,
    "placa": "RFU8J85",
    "produto": "Cimento ensacado",
    "tipo": "FOB"
  },
  {
    "posicao": 25,
    "placa": "RHG8J72",
    "produto": "Cimento ensacado",
    "tipo": "FOB"
  },
  {
    "posicao": 26,
    "placa": "MJT0E50",
    "produto": "Cimento ensacado",
    "tipo": "FOB"
  },
  {
    "posicao": 27,
    "placa": "SFE2B25",
    "produto": "Cimento ensacado",
    "tipo": "FOB"
  },
  {
    "posicao": 28,
    "placa": "DBM4B19",
    "produto": "Cimento ensacado",
    "tipo": "FOB"
  },
  {
    "posicao": 29,
    "placa": "JAH3C52",
    "produto": "Cimento ensacado",
    "tipo": "FOB"
  },
  {
    "posicao": 30,
    "placa": "GPZ4802",
    "produto": "Cimento ensacado",
    "tipo": "FOB"
  },
  {
    "posicao": 31,
    "placa": "GMO9441",
    "produto": "Cimento ensacado",
    "tipo": "FOB"
  },
  {
    "posicao": 32,
    "placa": "EXO2F41",
    "produto": "Cimento ensacado",
    "tipo": "FOB"
  },
  {
    "posicao": 33,
    "placa": "NDR1H94",
    "produto": "Cimento ensacado",
    "tipo": "FOB"
  },
  {
    "posicao": 34,
    "placa": "BTO6987",
    "produto": "Cimento ensacado",
    "tipo": "FOB"
  },
  {
    "posicao": 35,
    "placa": "EJW9D94",
    "produto": "Cimento ensacado",
    "tipo": "FOB"
  },
  {
    "posicao": 36,
    "placa": "SIK2E77",
    "produto": "Cimento ensacado",
    "tipo": "FOB"
  },
  {
    "posicao": 37,
    "placa": "RHP2G89",
    "produto": "Cimento ensacado",
    "tipo": "FOB"
  },
  {
    "posicao": 38,
    "placa": "GXH6490",
    "produto": "Cimento ensacado",
    "tipo": "FOB"
  },
  {
    "posicao": 39,
    "placa": "TAT8A99",
    "produto": "Cimento ensacado",
    "tipo": "FOB"
  },
  {
    "posicao": 40,
    "placa": "QOX6I81",
    "produto": "Cimento ensacado",
    "tipo": "FOB"
  },
  {
    "posicao": 41,
    "placa": "TEG5C77",
    "produto": "Cimento ensacado",
    "tipo": "FOB"
  },
  {
    "posicao": 42,
    "placa": "IUL8A22",
    "produto": "Cimento ensacado",
    "tipo": "FOB"
  },
  {
    "posicao": 43,
    "placa": "SUX6D24",
    "produto": "Cimento ensacado",
    "tipo": "FOB"
  },
  {
    "posicao": 44,
    "placa": "QWV2257",
    "produto": "Cimento ensacado",
    "tipo": "FOB"
  },
  {
    "posicao": 45,
    "placa": "OPB8A50",
    "produto": "Cimento ensacado",
    "tipo": "FOB"
  },
  {
    "posicao": 46,
    "placa": "ESS4E71",
    "produto": "Cimento ensacado",
    "tipo": "FOB"
  },
  {
    "posicao": 47,
    "placa": "TDW5D18",
    "produto": "Cimento ensacado",
    "tipo": "FOB"
  },
  {
    "posicao": 48,
    "placa": "QOQ6B06",
    "produto": "Cimento ensacado",
    "tipo": "FOB"
  },
  {
    "posicao": 49,
    "placa": "GSH6783",
    "produto": "Cimento ensacado",
    "tipo": "FOB"
  },
  {
    "posicao": 50,
    "placa": "ANS0I36",
    "produto": "Cimento ensacado",
    "tipo": "FOB"
  },
  {
    "posicao": 51,
    "placa": "PUJ9F45",
    "produto": "Cimento ensacado",
    "tipo": "FOB"
  },
  {
    "posicao": 52,
    "placa": "AYC7I70",
    "produto": "Cimento ensacado",
    "tipo": "FOB"
  },
  {
    "posicao": 53,
    "placa": "OPM2E05",
    "produto": "Cimento ensacado",
    "tipo": "FOB"
  },
  {
    "posicao": 54,
    "placa": "MIM6I73",
    "produto": "Cimento ensacado",
    "tipo": "FOB"
  },
  {
    "posicao": 55,
    "placa": "JBC5C48",
    "produto": "Cimento ensacado",
    "tipo": "FOB"
  },
  {
    "posicao": 56,
    "placa": "RHL0H12",
    "produto": "Cimento ensacado",
    "tipo": "FOB"
  }
]
