[
  {
    "posicao": 1,
    "placa": "FYH8A66",
    "produto": "Cimento ensacado",
    "tipo": "FOB"
  },
  {
    "posicao": 2,
    "placa": "RMO4J01",
    "produto": "Cimento ensacado",
    "tipo": "FOB"
  },
  {
    "posicao": 3,
    "placa": "QXQ2D07",
    "produto": "Cimento ensacado",
    "tipo": "FOB"
  },
  {
    "posicao": 4,
    "placa": "EFO0A83",
    "produto": "Cimento ensacado",
    "tipo": "FOB"
  },
  {
    "posicao": 5,
    "placa": "KEA0J23",
    "produto": "Cimento ensacado",
    "tipo": "FOB"
  },
  {
    "posicao": 6,
    "placa": "QUG8528",
    "produto": "Cimento ensacado",
    "tipo": "FOB"
  },
  {
    "posicao": 7,
    "placa": "HNM3C88",
    "produto": "Cimento ensacado",
    "tipo": "FOB"
  },
  {
    "posicao": 8,
    "placa": "GJC6G22",
    "produto": "Cimento ensacado",
    "tipo": "FOB"
  },
  {
    "posicao": 9,
    "placa": "QXM7794",
    "produto": "Cimento ensacado",
    "tipo": "FOB"
  },
  {
    "posicao": 10,
    "placa": "KEG9G43",
    "produto": "Cimento ensacado",
    "tipo": "FOB"
  }
]
