[
  {
    "posicao": 1,
    "placa": "AZR5E48",
    "produto": "Cimento granel",
    "tipo": "FOB"
  },
  {
    "posicao": 2,
    "placa": "AZR5F44",
    "produto": "Cimento granel",
    "tipo": "FOB"
  },
  {
    "posicao": 3,
    "placa": "QWR3A19",
    "produto": "Cimento granel",
    "tipo": "FOB"
  },
  {
    "posicao": 1,
    "placa": "OOX3D48",
    "produto": "Cimento ensacado",
    "tipo": "FCA"
  },
  {
    "posicao": 1,
    "placa": "EHX1G42",
    "produto": "Cimento ensacado",
    "tipo": "FOB"
  },
  {
    "posicao": 2,
    "placa": "CXO0I65",
    "produto": "Cimento ensacado",
    "tipo": "FOB"
  },
  {
    "posicao": 3,
    "placa": "UEY6A19",
    "produto": "Cimento ensacado",
    "tipo": "FOB"
  },
  {
    "posicao": 4,
    "placa": "SMI9A77",
    "produto": "Cimento ensacado",
    "tipo": "FOB"
  },
  {
    "posicao": 5,
    "placa": "APV6227",
    "produto": "Cimento ensacado",
    "tipo": "FOB"
  },
  {
    "posicao": 6,
    "placa": "FYT5G81",
    "produto": "Cimento ensacado",
    "tipo": "FOB"
  },
  {
    "posicao": 7,
    "placa": "QMT9G09",
    "produto": "Cimento ensacado",
    "tipo": "FOB"
  },
  {
    "posicao": 8,
    "placa": "OXK4J30",
    "produto": "Cimento ensacado",
    "tipo": "FOB"
  },
  {
    "posicao": 9,
    "placa": "RLB9H19",
    "produto": "Cimento ensacado",
    "tipo": "FOB"
  },
  {
    "posicao": 10,
    "placa": "RVH4C08",
    "produto": "Cimento ensacado",
    "tipo": "FOB"
  },
  {
    "posicao": 11,
    "placa": "PDQ2C61",
    "produto": "Cimento ensacado",
    "tipo": "FOB"
  },
  {
    "posicao": 12,
    "placa": "PRM0E66",
    "produto": "Cimento ensacado",
    "tipo": "FOB"
  },
  {
    "posicao": 13,
    "placa": "SFG5D80",
    "produto": "Cimento ensacado",
    "tipo": "FOB"
  }
]