[
  {
    "posicao": 1,
    "placa": "NTN7J26",
    "produto": "Cimento granel",
    "tipo": "FOB"
  },
  {
    "posicao": 1,
    "placa": "RXL5H10",
    "produto": "Cimento ensacado",
    "tipo": "FOB"
  },
  {
    "posicao": 2,
    "placa": "PUS5431",
    "produto": "Cimento ensacado",
    "tipo": "FOB"
  },
  {
    "posicao": 3,
    "placa": "SUT7F74",
    "produto": "Cimento ensacado",
    "tipo": "FOB"
  },
  {
    "posicao": 4,
    "placa": "TEA8A31",
    "produto": "Cimento ensacado",
    "tipo": "FOB"
  },
  {
    "posicao": 5,
    "placa": "GZV1I42",
    "produto": "Cimento ensacado",
    "tipo": "FOB"
  },
  {
    "posicao": 6,
    "placa": "QAB1H77",
    "produto": "Cimento ensacado",
    "tipo": "FOB"
  },
  {
    "posicao": 7,
    "placa": "HIH2F58",
    "produto": "Cimento ensacado",
    "tipo": "FOB"
  },
  {
    "posicao": 8,
    "placa": "RNT3D59",
    "produto": "Cimento ensacado",
    "tipo": "FOB"
  },
  {
    "posicao": 9,
    "placa": "SXQ2F13",
    "produto": "Cimento ensacado",
    "tipo": "FOB"
  },
  {
    "posicao": 10,
    "placa": "EFO0A83",
    "produto": "Cimento ensacado",
    "tipo": "FOB"
  },
  {
    "posicao": 11,
    "placa": "FEI8A35",
    "produto": "Cimento ensacado",
    "tipo": "FOB"
  },
  {
    "posicao": 12,
    "placa": "OOW0044",
    "produto": "Cimento ensacado",
    "tipo": "FOB"
  },
  {
    "posicao": 13,
    "placa": "ACS8A52",
    "produto": "Cimento ensacado",
    "tipo": "FOB"
  },
  {
    "posicao": 14,
    "placa": "RLK6I43",
    "produto": "Cimento ensacado",
    "tipo": "FOB"
  },
  {
    "posicao": 15,
    "placa": "SHU9G11",
    "produto": "Cimento ensacado",
    "tipo": "FOB"
  },
  {
    "posicao": 16,
    "placa": "SIG7I72",
    "produto": "Cimento ensacado",
    "tipo": "FOB"
  },
  {
    "posicao": 17,
    "placa": "QMT9G09",
    "produto": "Cimento ensacado",
    "tipo": "FOB"
  },
  {
    "posicao": 18,
    "placa": "RQZ6B50",
    "produto": "Cimento ensacado",
    "tipo": "FOB"
  },
  {
    "posicao": 19,
    "placa": "QXY9E78",
    "produto": "Cimento ensacado",
    "tipo": "FOB"
  },
  {
    "posicao": 20,
    "placa": "RTQ7C21",
    "produto": "Cimento ensacado",
    "tipo": "FOB"
  },
  {
    "posicao": 21,
    "placa": "MVI7J61",
    "produto": "Cimento ensacado",
    "tipo": "FOB"
  },
  {
    "posicao": 22,
    "placa": "BWO7086",
    "produto": "Cimento ensacado",
    "tipo": "FOB"
  }
]