[
  {
    "posicao": 1,
    "placa": "SRU1G84",
    "produto": "Cimento ensacado",
    "tipo": "Transferencia (FCA)"
  },
  {
    "posicao": 1,
    "placa": "GSH6J71",
    "produto": "Cimento ensacado",
    "tipo": "FOB"
  },
  {
    "posicao": 2,
    "placa": "QDY8G65",
    "produto": "Cimento ensacado",
    "tipo": "FOB"
  },
  {
    "posicao": 3,
    "placa": "OBJ9D51",
    "produto": "Cimento ensacado",
    "tipo": "FOB"
  },
  {
    "posicao": 4,
    "placa": "IIV5A08",
    "produto": "Cimento ensacado",
    "tipo": "FOB"
  },
  {
    "posicao": 5,
    "placa": "AKV6I04",
    "produto": "Cimento ensacado",
    "tipo": "FOB"
  }
]