[
  {
    "posicao": 1,
    "placa": "SWX3G54",
    "produto": "Cimento granel",
    "tipo": "FOB"
  },
  {
    "posicao": 1,
    "placa": "ERR9H46",
    "produto": "Cimento ensacado",
    "tipo": "FOB"
  },
  {
    "posicao": 2,
    "placa": "EKD5F50",
    "produto": "Cimento ensacado",
    "tipo": "FOB"
  },
  {
    "posicao": 3,
    "placa": "IHD0A57",
    "produto": "Cimento ensacado",
    "tipo": "FOB"
  },
  {
    "posicao": 4,
    "placa": "RQN1E78",
    "produto": "Cimento ensacado",
    "tipo": "FOB"
  },
  {
    "posicao": 5,
    "placa": "TCN1F98",
    "produto": "Cimento ensacado",
    "tipo": "FOB"
  },
  {
    "posicao": 6,
    "placa": "RXZ3J90",
    "produto": "Cimento ensacado",
    "tipo": "FOB"
  },
  {
    "posicao": 7,
    "placa": "MRX5576",
    "produto": "Cimento ensacado",
    "tipo": "FOB"
  }
]
